{
  "Id": "Loop",
  "Description": "Loop nodes a set amount of times",
  "Title": "Loop Operations",
  "Color": "purple",
  "Content": [
    {
      "Id": "StoredIndexName",
      "Type": "SmallString",
      "Options": {
        "Description": "The index to jump to repeat the loop",
        "Label": "Stored Index Name",
        "Width": 150
      }
    },
    {
      "Id": "AdditionalRepetitions",
      "Type": "Int",
      "Options": {
        "Description": "The extra amount of times to repeat the loop",
        "Label": "Additional Repetitions"
      }
    }
  ],
  "Inputs": [
    {
      "Id": "OperationPin",
      "Type": "Operation",
      "Multiple": false,
      "Color": "blue"
    }
  ],
  "Schema": {
    "Id": "loop",
    "StoredIndexName": "StoredIndexName",
    "AdditionalRepetitions": "AdditionalRepetitions"
  }
}
